qdrl/__init__.py
qdrl-0.0.0.dist-info/METADATA
qdrl-0.0.0.dist-info/WHEEL
qdrl-0.0.0.dist-info/top_level.txt
qdrl-0.0.0.dist-info/RECORD
