Metadata-Version: 2.2
Name: qdrl
Version: 0.0.0
Summary: Coming soon - Under construction
Author-email: Quang Phong <quang.phong@outlook.com>
